CHANGELOG.md
blitzly/etc/utils.py
blitzly/plots/bar.py
blitzly/plots/dumbbell.py
blitzly/plots/histogram.py
blitzly/plots/matrix.py
blitzly/plots/scatter.py
blitzly/plots/slope.py
blitzly/subplots.py
blitzly-0.6.2.dist-info/METADATA
blitzly-0.6.2.dist-info/WHEEL
blitzly-0.6.2.dist-info/LICENSE
blitzly-0.6.2.dist-info/RECORD
