Metadata-Version: 2.1
Name: blitzly
Version: 0.6.2
Summary: Lightning-fast way to get plots with Plotly
Home-page: https://github.com/invia-flights/blitzly
License: MIT
Keywords: python,data science,analytics,plotly,plotting
Author: Christopher Lemke
Author-email: christopher.lemke@invia.de
Requires-Python: >=3.8,<3.12
Classifier: Intended Audience :: Science/Research
Classifier: License :: OSI Approved :: MIT License
Classifier: Natural Language :: English
Classifier: Programming Language :: Python :: 3
Classifier: Programming Language :: Python :: 3.8
Classifier: Programming Language :: Python :: 3.9
Classifier: Programming Language :: Python :: 3.10
Classifier: Programming Language :: Python :: 3.11
Classifier: Topic :: Scientific/Engineering :: Information Analysis
Classifier: Topic :: Scientific/Engineering :: Visualization
Classifier: Typing :: Typed
Requires-Dist: nbformat (==5.7.2)
Requires-Dist: numpy (==1.23.5)
Requires-Dist: pandas (==1.5.2)
Requires-Dist: plotly (==5.13.0)
Requires-Dist: scikit-learn (==1.2.0)
Project-URL: Changelog, https://github.com/invia-flights/blitzly/blob/main/CHANGELOG.md
Project-URL: Contributing, https://github.com/invia-flights/blitzly/blob/main/docs/CONTRIBUTING.md
Project-URL: Documentation, https://invia-flights.github.io/blitzly
Project-URL: Discussions, https://github.com/invia-flights/blitzly/discussions
Project-URL: Issues, https://github.com/invia-flights/blitzly/issues
Project-URL: Repository, https://github.com/invia-flights/blitzly
